AUTHORS
LICENSE
MANIFEST.in
README.rst
setup.cfg
setup.py
django_markupmirror.egg-info/PKG-INFO
django_markupmirror.egg-info/SOURCES.txt
django_markupmirror.egg-info/dependency_links.txt
django_markupmirror.egg-info/not-zip-safe
django_markupmirror.egg-info/top_level.txt
docs/Makefile
docs/changelog.rst
docs/conf.py
docs/feincms.rst
docs/index.rst
docs/installation.rst
docs/quickstart.rst
docs/usage.rst
docs/_build/.keep
docs/_coverage/.keep
docs/_static/.keep
docs/_templates/.keep
markupmirror/__init__.py
markupmirror/exceptions.py
markupmirror/fields.py
markupmirror/models.py
markupmirror/settings.py
markupmirror/urls.py
markupmirror/views.py
markupmirror/widgets.py
markupmirror/feincms/__init__.py
markupmirror/feincms/models.py
markupmirror/locale/de/LC_MESSAGES/django.mo
markupmirror/locale/de/LC_MESSAGES/django.po
markupmirror/locale/en/LC_MESSAGES/django.mo
markupmirror/locale/en/LC_MESSAGES/django.po
markupmirror/markup/__init__.py
markupmirror/markup/base.py
markupmirror/markup/html.py
markupmirror/markup/markdown_.py
markupmirror/markup/plaintext.py
markupmirror/markup/restructuredtext.py
markupmirror/markup/textile_.py
markupmirror/static/markupmirror/codemirror.css
markupmirror/static/markupmirror/codemirror.js
markupmirror/static/markupmirror/codemirror.min.css
markupmirror/static/markupmirror/codemirror.min.js
markupmirror/static/markupmirror/jquery-1.7.2.min.js
markupmirror/static/markupmirror/jquery.cookie.min.js
markupmirror/static/markupmirror/markupmirror.css
markupmirror/static/markupmirror/markupmirror.js
markupmirror/static/markupmirror/normalize.css
markupmirror/static/markupmirror/normalize.min.css
markupmirror/static/markupmirror/lib/codemirror.css
markupmirror/static/markupmirror/lib/codemirror.js
markupmirror/static/markupmirror/lib/util/dialog.css
markupmirror/static/markupmirror/lib/util/dialog.js
markupmirror/static/markupmirror/lib/util/search.js
markupmirror/static/markupmirror/lib/util/simple-hint.css
markupmirror/static/markupmirror/lib/util/simple-hint.js
markupmirror/static/markupmirror/mode/css/css.js
markupmirror/static/markupmirror/mode/htmlmixed/htmlmixed.js
markupmirror/static/markupmirror/mode/javascript/javascript.js
