Metadata-Version: 1.1
Name: django-markupmirror
Version: 0.2a1
Summary: Django field and widget for editing markup content (PlainText, HTML,
Home-page: https://bitbucket.org/fabianbuechler/django-markupmirror
Author: Fabian Büchler
Author-email: fabian.buechler@gmail.com
License: BSD License
Keywords: django markup field widget codemirror
Platform: OS Independent
Classifier: Development Status :: 4 - Beta
Classifier: Framework :: Django
Classifier: Intended Audience :: Developers
Classifier: License :: OSI Approved :: BSD License
Classifier: Natural Language :: English
Classifier: Operating System :: OS Independent
Classifier: Programming Language :: Python
Classifier: Programming Language :: JavaScript
Classifier: Environment :: Web Environment
Classifier: Topic :: Software Development :: Libraries :: Python Modules
Classifier: Topic :: Text Processing :: Markup
